gegd/__init__.py
gegd/optimizer/ACMA_ES.py
gegd/optimizer/AF_BL.py
gegd/optimizer/AF_CMA_ES.py
gegd/optimizer/AF_GA.py
gegd/optimizer/AF_NES.py
gegd/optimizer/AF_PSO.py
gegd/optimizer/AF_STE.py
gegd/optimizer/CMA_EG.py
gegd/optimizer/GEGD.py
gegd/optimizer/TF.py
gegd/optimizer/TF_BFGS.py
gegd/optimizer/__init__.py
gegd/parameter_processing/__init__.py
gegd/parameter_processing/bilevel_design_generator.py
gegd/parameter_processing/density_transforms.py
gegd/parameter_processing/feasible_design_generator_python.py
gegd/parameter_processing/symmetry_operations.py
gegd/parameter_processing/test_batch_processing.py
gegd/parameter_processing/feasible_design_generator/apply_symmetry_float.c
gegd/parameter_processing/feasible_design_generator/apply_symmetry_float.h
gegd/parameter_processing/feasible_design_generator/apply_symmetry_int.c
gegd/parameter_processing/feasible_design_generator/apply_symmetry_int.h
gegd/parameter_processing/feasible_design_generator/fdg.cpython-312-x86_64-linux-gnu.so
gegd/parameter_processing/feasible_design_generator/fill_required_pixels.c
gegd/parameter_processing/feasible_design_generator/fill_required_pixels.h
gegd/parameter_processing/feasible_design_generator/find_index_max.c
gegd/parameter_processing/feasible_design_generator/find_index_max.h
gegd/parameter_processing/feasible_design_generator/main_loop.c
gegd/parameter_processing/feasible_design_generator/main_loop.h
gegd/parameter_processing/feasible_design_generator/make_feasible.c
gegd/parameter_processing/feasible_design_generator/make_feasible.h
gegd/parameter_processing/feasible_design_generator/make_touch.c
gegd/parameter_processing/feasible_design_generator/make_touch.h
gegd/parameter_processing/feasible_design_generator/parallelize.c
gegd/parameter_processing/feasible_design_generator/parallelize.h
gegd/parameter_processing/feasible_design_generator/touch2pix.c
gegd/parameter_processing/feasible_design_generator/touch2pix.h
gegd-0.5.2.dist-info/LICENSE
gegd-0.5.2.dist-info/METADATA
gegd-0.5.2.dist-info/WHEEL
gegd-0.5.2.dist-info/top_level.txt
gegd-0.5.2.dist-info/RECORD
